langchain_mixedbread_ai/__init__.py
langchain_mixedbread_ai/client.py
langchain_mixedbread_ai/embeddings.py
langchain_mixedbread_ai/py.typed
langchain_mixedbread_ai/rerank.py
langchain_mixedbread_ai-0.1.0.dist-info/LICENSE
langchain_mixedbread_ai-0.1.0.dist-info/METADATA
langchain_mixedbread_ai-0.1.0.dist-info/WHEEL
langchain_mixedbread_ai-0.1.0.dist-info/RECORD
