Metadata-Version: 2.1
Name: langchain-mixedbread-ai
Version: 0.1.0
Summary: An integration package connecting Mixedbread AI and LangChain
Home-page: https://github.com/mixedbread-ai/langchain-mixedbread-ai
License: MIT
Author: mixedbread.ai
Author-email: support@mixedbread.ai
Requires-Python: >=3.8.1,<4.0
Classifier: License :: OSI Approved :: MIT License
Classifier: Programming Language :: Python :: 3
Classifier: Programming Language :: Python :: 3.9
Classifier: Programming Language :: Python :: 3.10
Classifier: Programming Language :: Python :: 3.11
Classifier: Programming Language :: Python :: 3.12
Requires-Dist: langchain-core (>=0.2.0,<0.3.0)
Requires-Dist: mixedbread-ai (>=2.2.6,<3.0.0)
Project-URL: Repository, https://github.com/mixedbread-ai/langchain-mixedbread-ai
Project-URL: Source Code, https://github.com/mixedbread-ai/langchain-mixedbread-ai.git/tree/main/libs/mixedbread-ai
